{
  "project_info": {
    "project_number": "17723568750",
    "firebase_url": "https://nature-and-ayurveda-942cf.firebaseio.com",
    "project_id": "nature-and-ayurveda-942cf",
    "storage_bucket": "nature-and-ayurveda-942cf.appspot.com"
  },
  "client": [
    {
      "client_info": {
        "mobilesdk_app_id": "1:17723568750:android:b40e03c0da88f73e",
        "android_client_info": {
          "package_name": "com.effigrity.ayurvedichomemedicine.free"
        }
      },
      "oauth_client": [
        {
          "client_id": "17723568750-sdlupko8juprjhbe8dokldu13hgbfp98.apps.googleusercontent.com",
          "client_type": 3
        }
      ],
      "api_key": [
        {
          "current_key": "AIzaSyA3cOrA1CCDNMsqDMW6Ml7odra5CoC7dyU"
        }
      ],
      "services": {
        "analytics_service": {
          "status": 1
        },
        "appinvite_service": {
          "status": 1,
          "other_platform_oauth_client": []
        },
        "ads_service": {
          "status": 2
        }
      }
    }
  ],
  "configuration_version": "1"
}